qlua/__init__.py
qlua/__init__.pyi
qlua/typing.py
qlua/conf/logging.conf
qlua/conf/meta.ini
qlua/examples/rpc.py
qlua/rpc/AddColumn_pb2.py
qlua/rpc/AddColumn_pb2.pyi
qlua/rpc/AddLabel_pb2.py
qlua/rpc/AddLabel_pb2.pyi
qlua/rpc/AllocTable_pb2.py
qlua/rpc/AllocTable_pb2.pyi
qlua/rpc/CalcBuySell_pb2.py
qlua/rpc/CalcBuySell_pb2.pyi
qlua/rpc/CancelParamRequest_pb2.py
qlua/rpc/CancelParamRequest_pb2.pyi
qlua/rpc/Clear_pb2.py
qlua/rpc/Clear_pb2.pyi
qlua/rpc/CreateWindow_pb2.py
qlua/rpc/CreateWindow_pb2.pyi
qlua/rpc/DelAllLabels_pb2.py
qlua/rpc/DelAllLabels_pb2.pyi
qlua/rpc/DelLabel_pb2.py
qlua/rpc/DelLabel_pb2.pyi
qlua/rpc/DeleteRow_pb2.py
qlua/rpc/DeleteRow_pb2.pyi
qlua/rpc/DestroyTable_pb2.py
qlua/rpc/DestroyTable_pb2.pyi
qlua/rpc/GetCell_pb2.py
qlua/rpc/GetCell_pb2.pyi
qlua/rpc/GetLabelParams_pb2.py
qlua/rpc/GetLabelParams_pb2.pyi
qlua/rpc/GetTableSize_pb2.py
qlua/rpc/GetTableSize_pb2.pyi
qlua/rpc/GetWindowCaption_pb2.py
qlua/rpc/GetWindowCaption_pb2.pyi
qlua/rpc/GetWindowRect_pb2.py
qlua/rpc/GetWindowRect_pb2.pyi
qlua/rpc/Highlight_pb2.py
qlua/rpc/Highlight_pb2.pyi
qlua/rpc/InsertRow_pb2.py
qlua/rpc/InsertRow_pb2.pyi
qlua/rpc/IsSubscribed_Level_II_Quotes_pb2.py
qlua/rpc/IsSubscribed_Level_II_Quotes_pb2.pyi
qlua/rpc/IsWindowClosed_pb2.py
qlua/rpc/IsWindowClosed_pb2.pyi
qlua/rpc/ParamRequest_pb2.py
qlua/rpc/ParamRequest_pb2.pyi
qlua/rpc/PrintDbgStr_pb2.py
qlua/rpc/PrintDbgStr_pb2.pyi
qlua/rpc/RGB_pb2.py
qlua/rpc/RGB_pb2.pyi
qlua/rpc/RPC_pb2.py
qlua/rpc/RPC_pb2.pyi
qlua/rpc/SearchItems_pb2.py
qlua/rpc/SearchItems_pb2.pyi
qlua/rpc/SetCell_pb2.py
qlua/rpc/SetCell_pb2.pyi
qlua/rpc/SetColor_pb2.py
qlua/rpc/SetColor_pb2.pyi
qlua/rpc/SetLabelParams_pb2.py
qlua/rpc/SetLabelParams_pb2.pyi
qlua/rpc/SetSelectedRow_pb2.py
qlua/rpc/SetSelectedRow_pb2.pyi
qlua/rpc/SetTableNotificationCallback_pb2.py
qlua/rpc/SetTableNotificationCallback_pb2.pyi
qlua/rpc/SetWindowCaption_pb2.py
qlua/rpc/SetWindowCaption_pb2.pyi
qlua/rpc/SetWindowPos_pb2.py
qlua/rpc/SetWindowPos_pb2.pyi
qlua-1.2.2.dist-info/LICENSE
qlua-1.2.2.dist-info/METADATA
qlua-1.2.2.dist-info/WHEEL
qlua-1.2.2.dist-info/top_level.txt
qlua-1.2.2.dist-info/RECORD
