Metadata-Version: 2.1
Name: qlua
Version: 1.2.2
Summary: Quik Lua RPC API.
Home-page: https://gitlab.com/abrosimov.a.a/qlua
Author: Anton Abrosimov
Author-email: anton@abrosimov.online
License: Apache Software License
Project-URL: Bug Tracker, https://gitlab.com/abrosimov.a.a/qlua/-/issues
Project-URL: Documentation, https://gitlab.com/abrosimov.a.a/qlua/-/wikis/home
Project-URL: Source Code, https://gitlab.com/abrosimov.a.a/qlua
Keywords: quik-lua-rpc,quik,arqa,trading,protobuf,zeromq
Platform: UNKNOWN
Classifier: Development Status :: 4 - Beta
Classifier: Topic :: Communications
Classifier: Topic :: Office/Business :: Financial
Classifier: Topic :: Software Development :: Libraries :: Python Modules
Classifier: Operating System :: OS Independent
Classifier: Programming Language :: Python :: 3 :: Only
Classifier: License :: OSI Approved :: Apache Software License
Requires-Python: >=3.6.0
Requires-Dist: wheel
Requires-Dist: protobuf (<4,>=3.7.1)
Requires-Dist: pyzmq
